nnfs/__init__.py
nnfs/activations.py
nnfs/layer.py
nnfs/loss.py
nnfs/metrics.py
nnfs/model.py
nnfs/optimizers.py
nnfs_implementation-0.0.1.dist-info/LICENSE
nnfs_implementation-0.0.1.dist-info/WHEEL
nnfs_implementation-0.0.1.dist-info/METADATA
nnfs_implementation-0.0.1.dist-info/RECORD
