Metadata-Version: 2.1
Name: nnfs-implementation
Version: 0.0.1
Summary: Impelementation of Neural Networks from Scratch based on this book: https://nnfs.io/
Home-page: https://github.com/mahyar24/NeuralNetFromScratch/
License: GPLv3
Keywords: Deep Learning,Neural Network,DL,ML,AI
Author: Mahyar Mahdavi
Author-email: Mahyar@Mahyar24.com
Requires-Python: >=3.9,<4.0
Classifier: License :: Other/Proprietary License
Classifier: Programming Language :: Python :: 3
Classifier: Programming Language :: Python :: 3.10
Classifier: Programming Language :: Python :: 3.9
Requires-Dist: numpy (>=1.23.1,<2.0.0)
Requires-Dist: tqdm (>=4.64.0,<5.0.0)
Project-URL: Repository, https://github.com/mahyar24/NeuralNetFromScratch/
